gff3tool-1.4.5.data/purelib/gff3tool/__init__.py
gff3tool-1.4.5.data/purelib/gff3tool/lib.md
gff3tool-1.4.5.data/purelib/gff3tool/bin/__init__.py
gff3tool-1.4.5.data/purelib/gff3tool/bin/gff3_QC.py
gff3tool-1.4.5.data/purelib/gff3tool/bin/gff3_fix.py
gff3tool-1.4.5.data/purelib/gff3tool/bin/gff3_merge.py
gff3tool-1.4.5.data/purelib/gff3tool/bin/gff3_sort.py
gff3tool-1.4.5.data/purelib/gff3tool/bin/gff3_to_fasta.py
gff3tool-1.4.5.data/purelib/gff3tool/bin/version.py
gff3tool-1.4.5.data/purelib/gff3tool/lib/__init__.py
gff3tool-1.4.5.data/purelib/gff3tool/lib/gff3_ID_generator.py
gff3tool-1.4.5.data/purelib/gff3tool/lib/id_processor.py
gff3tool-1.4.5.data/purelib/gff3tool/lib/replace_OGS.py
gff3tool-1.4.5.data/purelib/gff3tool/lib/utils.py
gff3tool-1.4.5.data/purelib/gff3tool/lib/ERROR/ERROR.py
gff3tool-1.4.5.data/purelib/gff3tool/lib/ERROR/__init__.py
gff3tool-1.4.5.data/purelib/gff3tool/lib/auto_assignment/create_annotation_summaries_nov21-7.pl
gff3tool-1.4.5.data/purelib/gff3tool/lib/auto_assignment/find_match.pl
gff3tool-1.4.5.data/purelib/gff3tool/lib/auto_assignment/gen_spreadsheet.pl
gff3tool-1.4.5.data/purelib/gff3tool/lib/check_gene_parent/find_wrongly_split_gene_parent.pl
gff3tool-1.4.5.data/purelib/gff3tool/lib/function4gff/__init__.py
gff3tool-1.4.5.data/purelib/gff3tool/lib/function4gff/function4gff.py
gff3tool-1.4.5.data/purelib/gff3tool/lib/gff3/__init__.py
gff3tool-1.4.5.data/purelib/gff3tool/lib/gff3/gff3.py
gff3tool-1.4.5.data/purelib/gff3tool/lib/gff3_fix/__init__.py
gff3tool-1.4.5.data/purelib/gff3tool/lib/gff3_fix/fix.py
gff3tool-1.4.5.data/purelib/gff3tool/lib/gff3_merge/__init__.py
gff3tool-1.4.5.data/purelib/gff3tool/lib/gff3_merge/auto_replace_tag.py
gff3tool-1.4.5.data/purelib/gff3tool/lib/gff3_merge/merge.py
gff3tool-1.4.5.data/purelib/gff3tool/lib/gff3_merge/revision.py
gff3tool-1.4.5.data/purelib/gff3tool/lib/inter_model/__init__.py
gff3tool-1.4.5.data/purelib/gff3tool/lib/inter_model/inter_model.py
gff3tool-1.4.5.dist-info/LICENSE.md
gff3tool-1.4.5.dist-info/METADATA
gff3tool-1.4.5.dist-info/WHEEL
gff3tool-1.4.5.dist-info/entry_points.txt
gff3tool-1.4.5.dist-info/top_level.txt
gff3tool-1.4.5.dist-info/RECORD
