Metadata-Version: 2.1
Name: gff3tool
Version: 1.4.5
Summary: Python programs for processing GFF3 files
Home-page: https://github.com/NAL-i5K/GFF3toolkit
Author: NAL i5k workspace
Author-email: i5k@ars.usda.gov
License: UNKNOWN
Project-URL: Source, https://github.com/NAL-i5K/GFF3toolkit
Project-URL: Bug Reports, https://github.com/NAL-i5K/GFF3toolkit/issues
Keywords: gff3 gff bioinformatics
Platform: UNKNOWN
Classifier: Development Status :: 5 - Production/Stable
Classifier: Operating System :: POSIX :: Linux
Classifier: Operating System :: Microsoft :: Windows
Classifier: Operating System :: MacOS :: MacOS X
Classifier: Intended Audience :: Science/Research
Classifier: Topic :: Scientific/Engineering :: Bio-Informatics
Classifier: License :: Public Domain
Classifier: Programming Language :: Python :: 2.7
